Metadata-Version: 2.1
Name: pyniel
Version: 0.1
Summary: Python tools for Yours Truly
Home-page: UNKNOWN
Author: Daniel Dugas
Author-email: UNKNOWN
License: UNKNOWN
Platform: UNKNOWN
